shinrai/__init__.py
shinrai/schemas/__init__.py
shinrai/schemas/conversation.py
shinrai-0.0.1.dist-info/licenses/LICENSE
shinrai-0.0.1.dist-info/METADATA
shinrai-0.0.1.dist-info/WHEEL
shinrai-0.0.1.dist-info/top_level.txt
shinrai-0.0.1.dist-info/RECORD
