Metadata-Version: 2.4
Name: shinrai
Version: 0.0.1
Summary: SHINrAI
Requires-Python: >=3.12
License-File: LICENSE
Dynamic: license-file
